thulearn2018/__init__.py
thulearn2018/browser-hyr.py
thulearn2018/browser.py
thulearn2018/filemanager.py
thulearn2018/jsonhelper.py
thulearn2018/learn-hyr.py
thulearn2018/learn.py
thulearn2018/settings.py
thulearn2018/soup.py
thulearn2018/utils-hyr.py
thulearn2018/utils.py
thulearn2018-2.4.9.dist-info/LICENSE
thulearn2018-2.4.9.dist-info/METADATA
thulearn2018-2.4.9.dist-info/WHEEL
thulearn2018-2.4.9.dist-info/entry_points.txt
thulearn2018-2.4.9.dist-info/top_level.txt
thulearn2018-2.4.9.dist-info/RECORD
