Metadata-Version: 2.1
Name: thulearn2018
Version: 2.4.9
Summary: Tools for Web Learning of Tsinghua University
Home-page: https://github.com/euxcet/thulearn2018
Author: Chengchi Zhou, Yingtian Liu, Yurui Hong
Author-email: zcc16@mails.tsinghua.edu.cn, liu-yt16@mails.tsinghua.edu.cn,yuruihong02@outlook.com
Classifier: Programming Language :: Python :: 3
Classifier: License :: OSI Approved :: MIT License
Classifier: Operating System :: OS Independent
License-File: LICENSE
Requires-Dist: beautifulsoup4>=4.6.0
Requires-Dist: bs4>=0.0.1
Requires-Dist: click>=7.0
Requires-Dist: requests>=2.18.4
Requires-Dist: requests-toolbelt
